document_processor/__init__.py
document_processor/__version__.py
document_processor/cloud_storage/__init__.py
document_processor/cloud_storage/main.py
document_processor/cloud_storage/provider/__init__.py
document_processor/cloud_storage/provider/_base_storage.py
document_processor/cloud_storage/provider/aws_storage.py
document_processor/cloud_storage/provider/azure_storage.py
document_processor/cloud_storage/provider/gcloud_storage.py
document_processor/cloud_storage/provider/models.py
document_processor/database/__init__.py
document_processor/database/main.py
document_processor/database/provider/__init__.py
document_processor/database/provider/_base_db.py
document_processor/database/provider/models.py
document_processor/database/provider/mongo_db.py
document_processor/database/provider/supabase_db.py
document_processor/fetch/__init__.py
document_processor/fetch/archiver/__init__.py
document_processor/fetch/collector/__init__.py
document_processor/fetch/collector/main.py
document_processor/fetch/collector/models.py
document_processor/fetch/collector/README.md
document_processor/fetch/downloader/__init__.py
document_processor/fetch/downloader/main.py
document_processor/store_configs/__init__.py
document_processor/store_configs/configure_html.py
document_processor/store_configs/models.py
document_processor/transform/__init__.py
document_processor/transform/main.py
document_processor/transform/sample_config.yaml
document_processor/transform/transformer/__init__.py
document_processor/transform/transformer/base_transformer.py
document_processor/transform/transformer/csv_transformer.py
document_processor/transform/transformer/html/__init__.py
document_processor/transform/transformer/html/html_transformer.py
document_processor/transform/transformer/html/parser/__init__.py
document_processor/transform/transformer/html/parser/base_parser.py
document_processor/transform/transformer/html/parser/beautiful_soup.py
document_processor/transform/transformer/image_transformer.py
sl_document_processor-0.0.10.0.dist-info/LICENSE
sl_document_processor-0.0.10.0.dist-info/METADATA
sl_document_processor-0.0.10.0.dist-info/WHEEL
sl_document_processor-0.0.10.0.dist-info/RECORD
